django_rest_framework_rules-0.1.1.dist-info/DESCRIPTION.rst
django_rest_framework_rules-0.1.1.dist-info/METADATA
django_rest_framework_rules-0.1.1.dist-info/RECORD
django_rest_framework_rules-0.1.1.dist-info/WHEEL
django_rest_framework_rules-0.1.1.dist-info/metadata.json
django_rest_framework_rules-0.1.1.dist-info/top_level.txt
rest_framework_rules/__init__.py
rest_framework_rules/decorators.py
rest_framework_rules/mixins.py
