Metadata-Version: 2.0
Name: django-rest-framework-rules
Version: 0.1.1
Summary: Django REST framework integration for django-rules
Home-page: https://github.com/escodebar/django-rest-framework-rules
Author: Pablo Escodebar
Author-email: escodebar@gmail.com
License: MIT
Download-URL: https://github.com/escodebar/django-rest-framework-rules/archive/v0.1.1.tar.gz
Platform: UNKNOWN
Classifier: Development Status :: 3 - Alpha
Classifier: Environment :: Web Environment
Classifier: Framework :: Django
Classifier: Intended Audience :: Developers
Classifier: License :: OSI Approved :: MIT License
Classifier: Operating System :: OS Independent
Classifier: Programming Language :: Python
Classifier: Programming Language :: Python :: 2.7
Classifier: Programming Language :: Python :: 3.5
Classifier: Programming Language :: Python :: 3.6
Requires-Python: >=2.7, >=3.5.*, <4
Requires-Dist: Django (>=1.9)
